<?xml version="1.0" encoding="ISO-8859-1" standalone="no"?>
<constraints xmlns="http://www.rte-france.com/dynawo">
  <constraint modelName="BEYREP1_1.1" description="U &gt; Umax" time="0.0000" type="Bus" kind="USupUmax" limit="6.5999999999999996" value="6.6939070852298048"/>
  <constraint modelName="PRINQP1_1" description="U &lt; Umin" time="0.0000" type="Bus" kind="UInfUmin" limit="19.200000000000003" value="18.721143318659585"/>
  <constraint modelName="PRINQP1_2" description="U &lt; Umin" time="0.0000" type="Bus" kind="UInfUmin" limit="19.200000000000003" value="18.696187008310538"/>
  <constraint modelName="TACONP1_1" description="U &lt; Umin" time="0.0000" type="Bus" kind="UInfUmin" limit="26.400000000000002" value="25.294866093134875"/>
  <constraint modelName="TUCOYP1_1" description="U &lt; Umin" time="0.0000" type="Bus" kind="UInfUmin" limit="8" value="7.7101948034951988"/>
  <constraint modelName="calculatedBus_PRINQP1_2" description="U &lt; Umin" time="0.0000" type="Bus" kind="UInfUmin" limit="19.200000000000003" value="18.696187008310538"/>
  <constraint modelName="calculatedBus_PRINQP1_3" description="U &lt; Umin" time="0.0000" type="Bus" kind="UInfUmin" limit="19.200000000000003" value="18.696187008310538"/>
  <constraint modelName="calculatedBus_PRINQP1_4" description="U &lt; Umin" time="0.0000" type="Bus" kind="UInfUmin" limit="19.200000000000003" value="18.721143318659585"/>
  <constraint modelName="calculatedBus_PRINQP1_5" description="U &lt; Umin" time="0.0000" type="Bus" kind="UInfUmin" limit="19.200000000000003" value="18.721143318659585"/>
  <constraint modelName="calculatedBus_TACONP1_1" description="U &lt; Umin" time="0.0000" type="Bus" kind="UInfUmin" limit="26.400000000000002" value="25.294866093134875"/>
  <constraint modelName="calculatedBus_TACONP1_2" description="U &lt; Umin" time="0.0000" type="Bus" kind="UInfUmin" limit="26.400000000000002" value="25.294866093134875"/>
  <constraint modelName="calculatedBus_TACONP1_3" description="U &lt; Umin" time="0.0000" type="Bus" kind="UInfUmin" limit="26.400000000000002" value="25.294866093134875"/>
  <constraint modelName="calculatedBus_TACONP1_4" description="U &lt; Umin" time="0.0000" type="Bus" kind="UInfUmin" limit="26.400000000000002" value="25.294866093134875"/>
  <constraint modelName="calculatedBus_TACONP1_5" description="U &lt; Umin" time="0.0000" type="Bus" kind="UInfUmin" limit="26.400000000000002" value="25.294866093134875"/>
  <constraint modelName="calculatedBus_TACONP1_6" description="U &lt; Umin" time="0.0000" type="Bus" kind="UInfUmin" limit="26.400000000000002" value="25.294866093134875"/>
  <constraint modelName="calculatedBus_TACONP1_7" description="U &lt; Umin" time="0.0000" type="Bus" kind="UInfUmin" limit="26.400000000000002" value="25.294866093134875"/>
  <constraint modelName="calculatedBus_TUCOYP1_1" description="U &lt; Umin" time="0.0000" type="Bus" kind="UInfUmin" limit="8" value="7.7101948034951988"/>
  <constraint modelName="calculatedBus_TUCOYP1_2" description="U &lt; Umin" time="0.0000" type="Bus" kind="UInfUmin" limit="8" value="7.7101948034951988"/>
  <constraint modelName="calculatedBus_TUCOYP1_3" description="U &lt; Umin" time="0.0000" type="Bus" kind="UInfUmin" limit="8" value="7.7101948034951988"/>
  <constraint modelName="calculatedBus_TUCOYP1_4" description="U &lt; Umin" time="0.0000" type="Bus" kind="UInfUmin" limit="8" value="7.7101948034951988"/>
  <constraint modelName="COR.PY763" description="overload 1200s side 2" time="50.0000" type="TwoWindingsTransformer" kind="OverloadUp" limit="1659" value="1690.0340430548413" side="2" acceptableDuration="1200"/>
  <constraint modelName="COR.PY763" description="permanent limit side 2" time="50.0000" type="TwoWindingsTransformer" kind="PATL" limit="1659" value="1690.0340430548413" side="2"/>
  <constraint modelName="COR.PY769" description="overload 1200s side 2" time="50.0000" type="TwoWindingsTransformer" kind="OverloadUp" limit="847" value="1114.0198627028426" side="2" acceptableDuration="1200"/>
  <constraint modelName="COR.PY769" description="overload 300s side 2" time="50.0000" type="TwoWindingsTransformer" kind="OverloadUp" limit="1105" value="1114.0198627028426" side="2" acceptableDuration="300"/>
  <constraint modelName="COR.PY769" description="permanent limit side 2" time="50.0000" type="TwoWindingsTransformer" kind="PATL" limit="847" value="1114.0198627028426" side="2"/>
  <constraint modelName="B.SSBP1_1.1" description="U &gt; Umax" time="60.0000" type="Bus" kind="USupUmax" limit="39.600000000000001" value="40.552086235122879"/>
  <constraint modelName="B.SSBP1_1.2" description="U &gt; Umax" time="60.0000" type="Bus" kind="USupUmax" limit="39.600000000000001" value="40.54331087064876"/>
  <constraint modelName="calculatedBus_B.SSBP1_2" description="U &gt; Umax" time="60.0000" type="Bus" kind="USupUmax" limit="39.600000000000001" value="40.552086235122879"/>
  <constraint modelName="calculatedBus_B.SSBP1_3" description="U &gt; Umax" time="60.0000" type="Bus" kind="USupUmax" limit="39.600000000000001" value="40.54331087064876"/>
</constraints>
